[
  {
    "ID": "f1d95bbe-b7e7-4823-9a8c-3df4854d83cb",
    "flights": [
      {
        "ID": "205fa017-1b4d-42b3-b44e-0eaa99db2278",
        "flight": {
          "ID": "124e4567-e89b-12d3-a456-426614174000",
          "from": {
            "ID": "123e4507-e89b-12d3-a456-426614174000",
            "name": "Bordeaux",
            "country": "France"
          },
          "too": {
            "ID": "123e4567-e89b-12d3-a456-426614174000",
            "name": "Paris",
            "country": "France"
          }
        },
        "date": {
          "date": "20/02/2023 08:56"
        },
        "quantity": 1,
        "ticket_price": 250.0,
        "price": 200.0,
        "percentageReduction": -20
      }
    ],
    "price": 200.0
  }
]